bondana_client/__init__.py
bondana_client/bondana_client.py
bondana_client-2025.10.17171328.dist-info/METADATA
bondana_client-2025.10.17171328.dist-info/WHEEL
bondana_client-2025.10.17171328.dist-info/top_level.txt
bondana_client-2025.10.17171328.dist-info/RECORD
