Metadata-Version: 2.4
Name: bondana_client
Version: 2025.10.17171328
Summary: Unofficial T-Bank wrapper
Home-page: https://github.com/Mixolap/bondana_client
Author: Mixolap
Author-email: mixolapus@yandex.ru
Requires-Python: >=3.5
Requires-Dist: tinkoff-investments
Dynamic: author
Dynamic: author-email
Dynamic: description
Dynamic: description-content-type
Dynamic: home-page
Dynamic: requires-dist
Dynamic: requires-python
Dynamic: summary
